{"name":"Sebarau Fall","description":"Sarawak must have many waterfalls, only known to the locals. , near to Kg Bidak, is one of them. This kampung is located off the road from Kuching to the Borneo Highland Resort. Beautiful countryside. You will pass the Giam cascades on your way, near to Kg Benuk. Park your car in Kg Bidak and ask for a guide to the waterfall. It is not far from the kampung.The trail is clear, but it is advisable to take a guide to the waterfall. There is a pool. During our visit the view of the upper fall was obstructed by fallen trees.The Sebarau Fall","state":"Sarawak","location":{"verbatimCoordinates":"N 01 13.09' E 110 18.85'","verbatimLatitude":"N 01 13.09'","verbatimLongitude":"E 110 18.85'","decimalLatitude":1.21817,"decimalLongitude":110.31417,"decimalCoordinates":"1.21817,110.31417"},"coordinates":"N 01 13.09'  E 110 18.85'","waterSource":"Stream","waterfallProfile":"Vertical fall","accessibility":"Trekking","imgDetails":{"imgFilename":["TNP3150078.JPG","TNP3150089.JPG","TNP3150076.JPG","TNP3150060.JPG","TNP3150064.JPG","TNP3150068.JPG"],"imgUrl":["http://waterfallsofmalaysia.com/images/126sebarau/tn/TNP3150078.JPG","http://waterfallsofmalaysia.com/images/126sebarau/tn/TNP3150089.JPG","http://waterfallsofmalaysia.com/images/126sebarau/tn/TNP3150076.JPG","http://waterfallsofmalaysia.com/images/126sebarau/tn/TNP3150060.JPG","http://waterfallsofmalaysia.com/images/126sebarau/tn/TNP3150064.JPG","http://waterfallsofmalaysia.com/images/126sebarau/tn/TNP3150068.JPG"],"imgDesc":["Sg Kita, near Kg Benuk, has nice cascades. Boats connect to the Sarawak Kiri river.","The Giam cascades","Trail head in Kg Bidak","Clear trail through bamboo forest","The Sebarau Fall","Nice pool"],"imgFullResFilename":["sebarau.jpg","P3150068.JPG","P3150076.JPG","P3150078.JPG","P3150060.JPG","P3150089.JPG","P3150064.JPG"]},"url":"126sebarau.php"}